qovery/__init__.py
qovery/api_client.py
qovery/configuration.py
qovery/exceptions.py
qovery/model_utils.py
qovery/rest.py
qovery/api/__init__.py
qovery/api/account_info_api.py
qovery/api/application_actions_api.py
qovery/api/application_configuration_api.py
qovery/api/application_database_api.py
qovery/api/application_deployment_history_api.py
qovery/api/application_environment_variable_api.py
qovery/api/application_event_api.py
qovery/api/application_logs_api.py
qovery/api/application_main_calls_api.py
qovery/api/application_metrics_api.py
qovery/api/application_secret_api.py
qovery/api/applications_api.py
qovery/api/backups_api.py
qovery/api/billing_api.py
qovery/api/cloud_provider_api.py
qovery/api/cloud_provider_credentials_api.py
qovery/api/clusters_api.py
qovery/api/custom_domain_api.py
qovery/api/database_actions_api.py
qovery/api/database_application_api.py
qovery/api/database_event_api.py
qovery/api/database_main_calls_api.py
qovery/api/database_metrics_api.py
qovery/api/databases_api.py
qovery/api/dependency_api.py
qovery/api/environment_actions_api.py
qovery/api/environment_deployment_history_api.py
qovery/api/environment_deployment_rule_api.py
qovery/api/environment_logs_api.py
qovery/api/environment_main_calls_api.py
qovery/api/environment_secret_api.py
qovery/api/environment_variable_api.py
qovery/api/environments_api.py
qovery/api/git_repositories_api.py
qovery/api/logical_database_api.py
qovery/api/members_api.py
qovery/api/organization_main_calls_api.py
qovery/api/project_deployment_rule_api.py
qovery/api/project_environment_variable_api.py
qovery/api/project_main_calls_api.py
qovery/api/project_secret_api.py
qovery/api/projects_api.py
qovery/api/referral__rewards_api.py
qovery/apis/__init__.py
qovery/model/__init__.py
qovery/model/account_info_edit_request.py
qovery/model/account_info_response.py
qovery/model/aliased_secret.py
qovery/model/application_current_scale_response.py
qovery/model/application_dependency_request.py
qovery-1.0.3.dist-info/METADATA
qovery-1.0.3.dist-info/WHEEL
qovery-1.0.3.dist-info/top_level.txt
qovery-1.0.3.dist-info/RECORD
