Metadata-Version: 2.1
Name: qovery
Version: 1.0.3
Summary: Qovery API
Home-page: 
Author: Qovery Product Team
Author-email: support+api+documentation@qovery.com
License: UNKNOWN
Keywords: OpenAPI,OpenAPI-Generator,Qovery API
Platform: UNKNOWN
Requires-Python: >=3.6
Requires-Dist: urllib3 (>=1.25.3)
Requires-Dist: python-dateutil
